flymefce/__init__.py
flymefce/compat.py
flymefce/exception.py
flymefce/fce_base_client.py
flymefce/fce_client_configuration.py
flymefce/fce_response.py
flymefce/protocol.py
flymefce/region.py
flymefce/utils.py
flymefce/auth/__init__.py
flymefce/auth/fce_credentials.py
flymefce/auth/fce_v1_signer.py
flymefce/http/__init__.py
flymefce/http/fce_http_client.py
flymefce/http/handler.py
flymefce/http/http_content_types.py
flymefce/http/http_headers.py
flymefce/http/http_methods.py
flymefce/retry/__init__.py
flymefce/retry/retry_policy.py
flymefce/services/__init__.py
flymefce/services/fos/__init__.py
flymefce/services/fos/canned_acl.py
flymefce/services/fos/fos_client.py
flymefce/services/fos/fos_handler.py
flymefce/services/fos/storage_class.py
flymefce/services/sts/__init__.py
flymefce/services/sts/sts_client.py
flymefce-1.0.3.dist-info/METADATA
flymefce-1.0.3.dist-info/WHEEL
flymefce-1.0.3.dist-info/top_level.txt
flymefce-1.0.3.dist-info/RECORD
